Workbook

Sheet Full Report
A1: Folder Path | B1: Bot Name | C1: Package Name | D1: Package Version | E1: Command Count
A2: Bots | B2: Daily_Health_Check | C2: Database | D2: 3.9.0-20250801-070000 | E2: 12
A3: Bots | B3: Daily_Health_Check | C3: Datetime | D3: 3.5.1-20250703-100000 | E3: 2
A4: Bots | B4: Daily_Health_Check | C4: String | D4: 3.8.1-20250822-093011 | E4: 17
A5: Bots | B5: Daily_Health_Check | C5: Browser | D5: 4.0.0-20251001-084500 | E5: 7
A6: Bots | B6: Daily_Health_Check | C6: Email | D6: 4.2.1-20250915-120000 | E6: 2
A7: Bots | B7: Cleanup_Temp_Files | C7: Credential Vault | D7: 3.0.0-20250301-100000 | E7: 8
A8: Bots | B8: Cleanup_Temp_Files | C8: Wait | D8: 3.0.2-20250210-100000 | E8: 3
A9: Bots | B9: Cleanup_Temp_Files | C9: Browser | D9: 4.0.0-20251001-084500 | E9: 18
A10: Bots\Finance | B10: Month_End_Close | C10: String | D10: 3.8.1-20250822-093011 | E10: 13
A11: Bots\Finance | B11: Month_End_Close | C11: PDF | D11: 3.7.0-20250812-101500 | E11: 2
A12: Bots\Finance | B12: Month_End_Close | C12: Email | D12: 4.2.1-20250915-120000 | E12: 8
A13: Bots\Finance | B13: Month_End_Close | C13: Folder | D13: 3.2.4-20250515-091500 | E13: 2
... A146: Bots\Utilities | B146: Archive_Logs | C146: Database | D146: 3.9.0-20250801-070000 | E146: 1

Sheet Bot Summary
A1: Folder Path | B1: Bot Name | C1: Packages Used | D1: Total Commands
A2: Bots | B2: Cleanup_Temp_Files | C2: =COUNTIFS('Full Report'!$B$2:$B$146,B2) -> 3 | D2: =SUMIFS('Full Report'!$E$2:$E$146,'Full Report'!$B$2:$B$146,B2) -> 29
A3: Bots | B3: Daily_Health_Check | C3: =COUNTIFS('Full Report'!$B$2:$B$146,B3) -> 5 | D3: =SUMIFS('Full Report'!$E$2:$E$146,'Full Report'!$B$2:$B$146,B3) -> 40
A4: Bots\Finance | B4: Bank_Reconciliation | C4: =COUNTIFS('Full Report'!$B$2:$B$146,B4) -> 5 | D4: =SUMIFS('Full Report'!$E$2:$E$146,'Full Report'!$B$2:$B$146,B4) -> 47
A5: Bots\Finance | B5: Expense_Report_Export | C5: =COUNTIFS('Full Report'!$B$2:$B$146,B5) -> 3 | D5: =SUMIFS('Full Report'!$E$2:$E$146,'Full Report'!$B$2:$B$146,B5) -> 41
A6: Bots\Finance | B6: Month_End_Close | C6: =COUNTIFS('Full Report'!$B$2:$B$146,B6) -> 6 | D6: =SUMIFS('Full Report'!$E$2:$E$146,'Full Report'!$B$2:$B$146,B6) -> 48
A7: Bots\Finance\Invoices | B7: Invoice_Approval | C7: =COUNTIFS('Full Report'!$B$2:$B$146,B7) -> 5 | D7: =SUMIFS('Full Report'!$E$2:$E$146,'Full Report'!$B$2:$B$146,B7) -> 52
A8: Bots\Finance\Invoices | B8: Invoice_Extraction | C8: =COUNTIFS('Full Report'!$B$2:$B$146,B8) -> 6 | D8: =SUMIFS('Full Report'!$E$2:$E$146,'Full Report'!$B$2:$B$146,B8) -> 60
A9: Bots\Finance\Invoices | B9: Invoice_Posting | C9: =COUNTIFS('Full Report'!$B$2:$B$146,B9) -> 3 | D9: =SUMIFS('Full Report'!$E$2:$E$146,'Full Report'!$B$2:$B$146,B9) -> 39
A10: Bots\Finance\Invoices | B10: Vendor_Match | C10: =COUNTIFS('Full Report'!$B$2:$B$146,B10) -> 6 | D10: =SUMIFS('Full Report'!$E$2:$E$146,'Full Report'!$B$2:$B$146,B10) -> 61
A11: Bots\HR | B11: Employee_Data_Sync | C11: =COUNTIFS('Full Report'!$B$2:$B$146,B11) -> 6 | D11: =SUMIFS('Full Report'!$E$2:$E$146,'Full Report'!$B$2:$B$146,B11) -> 65
A12: Bots\HR | B12: Leave_Balance_Update | C12: =COUNTIFS('Full Report'!$B$2:$B$146,B12) -> 3 | D12: =SUMIFS('Full Report'!$E$2:$E$146,'Full Report'!$B$2:$B$146,B12) -> 32
A13: Bots\HR\Onboarding | B13: Equipment_Request | C13: =COUNTIFS('Full Report'!$B$2:$B$146,B13) -> 4 | D13: =SUMIFS('Full Report'!$E$2:$E$146,'Full Report'!$B$2:$B$146,B13) -> 39
... A34: Bots\Utilities | B34: Send_Notification | C34: =COUNTIFS('Full Report'!$B$2:$B$146,B34) -> 4 | D34: =SUMIFS('Full Report'!$E$2:$E$146,'Full Report'!$B$2:$B$146,B34) -> 18

Sheet Package Summary
A1: Package Name | B1: Package Version | C1: Bots Using It | D1: Total Commands
A2: Browser | B2: 4.0.0-20251001-084500 | C2: =COUNTIFS('Full Report'!$C$2:$C$146,A2,'Full Report'!$D$2:$D$146,B2) -> 11 | D2: =SUMIFS('Full Report'!$E$2:$E$146,'Full Report'!$C$2:$C$146,A2,'Full Report'!$D$2:$D$146,B2) -> 111
A3: Credential Vault | B3: 3.0.0-20250301-100000 | C3: =COUNTIFS('Full Report'!$C$2:$C$146,A3,'Full Report'!$D$2:$D$146,B3) -> 7 | D3: =SUMIFS('Full Report'!$E$2:$E$146,'Full Report'!$C$2:$C$146,A3,'Full Report'!$D$2:$D$146,B3) -> 71
A4: Database | B4: 3.9.0-20250801-070000 | C4: =COUNTIFS('Full Report'!$C$2:$C$146,A4,'Full Report'!$D$2:$D$146,B4) -> 6 | D4: =SUMIFS('Full Report'!$E$2:$E$146,'Full Report'!$C$2:$C$146,A4,'Full Report'!$D$2:$D$146,B4) -> 60
A5: Datetime | B5: 3.5.1-20250703-100000 | C5: =COUNTIFS('Full Report'!$C$2:$C$146,A5,'Full Report'!$D$2:$D$146,B5) -> 7 | D5: =SUMIFS('Full Report'!$E$2:$E$146,'Full Report'!$C$2:$C$146,A5,'Full Report'!$D$2:$D$146,B5) -> 61
A6: Dictionary | B6: 3.1.2-20250422-082200 | C6: =COUNTIFS('Full Report'!$C$2:$C$146,A6,'Full Report'!$D$2:$D$146,B6) -> 5 | D6: =SUMIFS('Full Report'!$E$2:$E$146,'Full Report'!$C$2:$C$146,A6,'Full Report'!$D$2:$D$146,B6) -> 56
A7: Email | B7: 4.2.1-20250915-120000 | C7: =COUNTIFS('Full Report'!$C$2:$C$146,A7,'Full Report'!$D$2:$D$146,B7) -> 15 | D7: =SUMIFS('Full Report'!$E$2:$E$146,'Full Report'!$C$2:$C$146,A7,'Full Report'!$D$2:$D$146,B7) -> 134
A8: Error handler | B8: 3.1.0-20250330-100000 | C8: =COUNTIFS('Full Report'!$C$2:$C$146,A8,'Full Report'!$D$2:$D$146,B8) -> 9 | D8: =SUMIFS('Full Report'!$E$2:$E$146,'Full Report'!$C$2:$C$146,A8,'Full Report'!$D$2:$D$146,B8) -> 103
A9: Excel advanced | B9: 12.3.0-20250910-101112 | C9: =COUNTIFS('Full Report'!$C$2:$C$146,A9,'Full Report'!$D$2:$D$146,B9) -> 4 | D9: =SUMIFS('Full Report'!$E$2:$E$146,'Full Report'!$C$2:$C$146,A9,'Full Report'!$D$2:$D$146,B9) -> 20
A10: File | B10: 3.4.0-20250611-101000 | C10: =COUNTIFS('Full Report'!$C$2:$C$146,A10,'Full Report'!$D$2:$D$146,B10) -> 5 | D10: =SUMIFS('Full Report'!$E$2:$E$146,'Full Report'!$C$2:$C$146,A10,'Full Report'!$D$2:$D$146,B10) -> 45
A11: Folder | B11: 3.2.4-20250515-091500 | C11: =COUNTIFS('Full Report'!$C$2:$C$146,A11,'Full Report'!$D$2:$D$146,B11) -> 5 | D11: =SUMIFS('Full Report'!$E$2:$E$146,'Full Report'!$C$2:$C$146,A11,'Full Report'!$D$2:$D$146,B11) -> 36
A12: List | B12: 3.0.5-20250410-080000 | C12: =COUNTIFS('Full Report'!$C$2:$C$146,A12,'Full Report'!$D$2:$D$146,B12) -> 7 | D12: =SUMIFS('Full Report'!$E$2:$E$146,'Full Report'!$C$2:$C$146,A12,'Full Report'!$D$2:$D$146,B12) -> 69
A13: Log to file | B13: 3.0.1-20250225-100000 | C13: =COUNTIFS('Full Report'!$C$2:$C$146,A13,'Full Report'!$D$2:$D$146,B13) -> 4 | D13: =SUMIFS('Full Report'!$E$2:$E$146,'Full Report'!$C$2:$C$146,A13,'Full Report'!$D$2:$D$146,B13) -> 49
... A21: Wait | B21: 3.0.2-20250210-100000 | C21: =COUNTIFS('Full Report'!$C$2:$C$146,A21,'Full Report'!$D$2:$D$146,B21) -> 10 | D21: =SUMIFS('Full Report'!$E$2:$E$146,'Full Report'!$C$2:$C$146,A21,'Full Report'!$D$2:$D$146,B21) -> 93

Sheet Read Me
A1: SAMPLE DATA ONLY
A2: All folder names, bot names, user names and counts in this workbook are made-up dummy values for documentation.
A3: Sheet layout is illustrative of the BotPackageInventory report (one row per bot / package / version).
